README.md
setup.py
tods/__init__.py
tods/run_tests.py
tods/schemas.py
tods/utils.py
tods.egg-info/PKG-INFO
tods.egg-info/SOURCES.txt
tods.egg-info/dependency_links.txt
tods.egg-info/entry_points.txt
tods.egg-info/requires.txt
tods.egg-info/top_level.txt
tods/data_processing/CategoricalToBinary.py
tods/data_processing/ColumnFilter.py
tods/data_processing/ContinuityValidation.py
tods/data_processing/DatasetToDataframe.py
tods/data_processing/DuplicationValidation.py
tods/data_processing/SKImputer.py
tods/data_processing/TimeIntervalTransform.py
tods/data_processing/TimeStampValidation.py
tods/data_processing/__init__.py
tods/detection_algorithm/AutoRegODetect.py
tods/detection_algorithm/DeepLog.py
tods/detection_algorithm/KDiscordODetect.py
tods/detection_algorithm/LSTMODetect.py
tods/detection_algorithm/MatrixProfile.py
tods/detection_algorithm/PCAODetect.py
tods/detection_algorithm/PyodABOD.py
tods/detection_algorithm/PyodAE.py
tods/detection_algorithm/PyodCBLOF.py
tods/detection_algorithm/PyodCOF.py
tods/detection_algorithm/PyodHBOS.py
tods/detection_algorithm/PyodIsolationForest.py
tods/detection_algorithm/PyodKNN.py
tods/detection_algorithm/PyodLODA.py
tods/detection_algorithm/PyodLOF.py
tods/detection_algorithm/PyodMoGaal.py
tods/detection_algorithm/PyodOCSVM.py
tods/detection_algorithm/PyodSOD.py
tods/detection_algorithm/PyodSoGaal.py
tods/detection_algorithm/PyodVAE.py
tods/detection_algorithm/Telemanom.py
tods/detection_algorithm/UODBasePrimitive.py
tods/detection_algorithm/__init__.py
tods/detection_algorithm/core/AutoRegOD.py
tods/detection_algorithm/core/CollectiveBase.py
tods/detection_algorithm/core/CollectiveCommonTest.py
tods/detection_algorithm/core/KDiscord.py
tods/detection_algorithm/core/LSTMOD.py
tods/detection_algorithm/core/MultiAutoRegOD.py
tods/detection_algorithm/core/PCA.py
tods/detection_algorithm/core/UODCommonTest.py
tods/detection_algorithm/core/__init__.py
tods/detection_algorithm/core/algorithm_implementation.py
tods/detection_algorithm/core/test_CollectiveBase.py
tods/detection_algorithm/core/utility.py
tods/detection_algorithm/core/utils/__init__.py
tods/detection_algorithm/core/utils/channel.py
