Metadata-Version: 1.0
Name: tods
Version: 0.0.2
Summary: Automated Time-series Outlier Detection System
Home-page: https://tods-doc.github.io
Author: DATA Lab@Texas A&M University
Author-email: khlai037@tamu.edu
License: UNKNOWN
Platform: UNKNOWN
